{
    "dev_acc_list": [
        0.9049429657791236,
        0.9505703422049618,
        0.950191570880862,
        0.9272030651337444,
        0.9157088122601856,
        0.9463601532563425,
        0.9233716475092248,
        0.9461538461534823,
        0.9499999999996347,
        0.9461538461534823
    ],
    "dev_dp_acc": 0.005036188511941461,
    "dev_dp_f1": 0.034053339287359666,
    "dev_dp_f1_weighted": 0.0064682730194118975,
    "dev_mean_acc": 0.9360656249331045,
    "dev_mean_f1": 0.7520418911555609,
    "dp_precision_bad": 0.0069361031066482925,
    "dp_precision_good": 0.00807916238562919,
    "dp_precision_ugly": 0.10408710460163936,
    "dp_recall_bad": 0.015005487073583812,
    "dp_recall_good": 0.0046448297463123145,
    "dp_recall_ugly": 0.10163114133418404,
    "elapsed_time": 213.79069395860037,
    "elapsed_time_list": [
        1661.0076460838318,
        1418.5997276306152,
        2136.5735783576965,
        1081.8774828910828,
        1155.4082503318787,
        1212.4472007751465,
        879.5440340042114,
        1371.742657661438,
        1001.5509023666382,
        908.6901574134827
    ],
    "experiment_name": "busson_model_D_1570096694.7148998",
    "f1_bad": 0.9039431900275421,
    "f1_bad_list": [
        0.8502994011976047,
        0.9257142857142858,
        0.9257142857142858,
        0.8926553672316384,
        0.8674698795180723,
        0.9204545454545454,
        0.888888888888889,
        0.9230769230769231,
        0.9265536723163842,
        0.9186046511627908
    ],
    "f1_dp_bad": 0.00829149175419903,
    "f1_dp_good": 0.002787094326886025,
    "f1_dp_ugly": 0.0926956084467379,
    "f1_good": 0.9655480720988472,
    "f1_good_list": [
        0.9461756373937678,
        0.9760479041916168,
        0.967359050445104,
        0.9640718562874252,
        0.9570200573065902,
        0.973293768545994,
        0.9583333333333334,
        0.9695121951219512,
        0.970059880239521,
        0.9736070381231672
    ],
    "f1_list": [
        0.5988250128637908,
        0.869214847615693,
        0.89769111205313,
        0.7401211957184758,
        0.6081633122748875,
        0.7793975861483279,
        0.6157407407407408,
        0.8308630393996248,
        0.8544267397408573,
        0.7259753250000812
    ],
    "f1_ugly": 0.38663441134029364,
    "f1_ugly_list": [
        0.0,
        0.7058823529411764,
        0.8,
        0.3636363636363636,
        0.0,
        0.4444444444444444,
        0.0,
        0.6,
        0.6666666666666665,
        0.28571428571428575
    ],
    "f1_weighted": 0.9322002536812578,
    "f1_weighted_list": [
        0.8925096198666767,
        0.9530427645204845,
        0.9496301277085071,
        0.9264632451619087,
        0.905169536956243,
        0.9435232384557054,
        0.9131545338441891,
        0.946868234954539,
        0.9496675488657628,
        0.9419736864785627
    ],
    "model_description": "inception network architecture",
    "model_name": "busson_model_D",
    "precision_bad": 0.903445420371621,
    "precision_bad_list": [
        0.8987341772151899,
        0.9310344827586207,
        0.9204545454545454,
        0.8777777777777778,
        0.9113924050632911,
        0.9101123595505618,
        0.8602150537634409,
        0.8842105263157894,
        0.9111111111111111,
        0.9294117647058824
    ],
    "precision_good": 0.9610454697953958,
    "precision_good_list": [
        0.907608695652174,
        0.9878787878787879,
        0.9644970414201184,
        0.9698795180722891,
        0.9226519337016574,
        0.9704142011834319,
        0.9583333333333334,
        0.99375,
        0.9759036144578314,
        0.9595375722543352
    ],
    "precision_ugly": 0.44621212121212117,
    "precision_ugly_list": [
        0.0,
        0.5454545454545454,
        1.0,
        0.4,
        0.0,
        0.6666666666666666,
        0.0,
        0.6,
        0.75,
        0.5
    ],
    "pred": [
        [
            1,
            0,
            0,
            1,
            0,
            0,
            1,
            0,
            1,
            1,
            1,
            0,
            1,
            0,
            1,
            1,
            0,
            0,
            1,
            0,
            0,
            0,
            0,
            1,
            0,
            0,
            0,
            0,
            0,
            0,
            0,
            1,
            0,
            0,
            0,
            0,
            0,
            1,
            0,
            0,
            0,
            0,
            0,
            0,
            0,
            0,
            1,
            1,
            0,
            0,
            0,
            1,
            0,
            0,
            0,
            0,
            0,
            0,
            1,
            0,
            0,
            1,
            0,
            0,
            1,
            0,
            1,
            1,
            0,
            0,
            0,
            0,
            0,
            1,
            1,
            0,
            0,
            1,
            0,
            1,
            0,
            0,
            0,
            0,
            1,
            1,
            0,
            0,
            0,
            0,
            0,
            0,
            0,
            1,
            1,
            1,
            0,
            0,
            0,
            0,
            1,
            0,
            1,
            1,
            0,
            1,
            0,
            0,
            0,
            1,
            0,
            1,
            0,
            0,
            0,
            0,
            0,
            0,
            0,
            1,
            0,
            1,
            0,
            1,
            0,
            1,
            0,
            0,
            1,
            0,
            0,
            0,
            0,
            0,
            0,
            1,
            0,
            1,
            1,
            1,
            1,
            0,
            1,
            1,
            0,
            0,
            0,
            1,
            0,
            1,
            1,
            0,
            0,
            1,
            1,
            0,
            0,
            0,
            0,
            0,
            0,
            1,
            0,
            0,
            0,
            0,
            0,
            0,
            0,
            0,
            0,
            0,
            0,
            0,
            0,
            0,
            1,
            1,
            0,
            0,
            1,
            0,
            1,
            0,
            0,
            0,
            0,
            1,
            0,
            1,
            0,
            0,
            1,
            1,
            0,
            0,
            0,
            0,
            1,
            1,
            1,
            0,
            0,
            1,
            0,
            0,
            0,
            0,
            0,
            1,
            0,
            0,
            0,
            0,
            0,
            1,
            1,
            0,
            0,
            0,
            0,
            0,
            1,
            1,
            0,
            0,
            0,
            0,
            0,
            0,
            0,
            0,
            1,
            0,
            0,
            1,
            0,
            1,
            0,
            0,
            0,
            1,
            0,
            0,
            1,
            0,
            0,
            0,
            0,
            0,
            0,
            0,
            0,
            0,
            0,
            0,
            0,
            0,
            0,
            0,
            1,
            1,
            1
        ],
        [
            0,
            0,
            0,
            0,
            0,
            1,
            0,
            0,
            0,
            0,
            1,
            1,
            1,
            1,
            0,
            0,
            1,
            1,
            0,
            0,
            1,
            0,
            1,
            1,
            1,
            0,
            0,
            0,
            0,
            0,
            1,
            1,
            0,
            0,
            0,
            1,
            0,
            1,
            0,
            1,
            1,
            0,
            1,
            1,
            1,
            0,
            0,
            0,
            1,
            0,
            0,
            0,
            0,
            0,
            0,
            1,
            0,
            0,
            1,
            1,
            0,
            0,
            0,
            0,
            1,
            0,
            0,
            1,
            0,
            0,
            1,
            0,
            0,
            0,
            0,
            0,
            1,
            0,
            0,
            0,
            0,
            0,
            0,
            0,
            0,
            0,
            0,
            1,
            0,
            2,
            0,
            0,
            1,
            1,
            1,
            1,
            0,
            0,
            0,
            1,
            0,
            1,
            1,
            1,
            0,
            1,
            0,
            0,
            0,
            0,
            0,
            1,
            1,
            0,
            1,
            0,
            0,
            2,
            2,
            0,
            2,
            0,
            0,
            0,
            1,
            1,
            0,
            0,
            1,
            0,
            0,
            1,
            0,
            1,
            1,
            0,
            0,
            0,
            1,
            1,
            0,
            0,
            0,
            0,
            0,
            0,
            0,
            1,
            2,
            1,
            0,
            0,
            0,
            0,
            1,
            0,
            0,
            1,
            0,
            1,
            0,
            0,
            0,
            0,
            1,
            0,
            0,
            1,
            1,
            0,
            1,
            1,
            0,
            0,
            0,
            1,
            0,
            1,
            0,
            0,
            0,
            1,
            1,
            0,
            1,
            1,
            0,
            0,
            1,
            2,
            0,
            1,
            2,
            1,
            0,
            1,
            0,
            0,
            0,
            0,
            0,
            0,
            1,
            0,
            0,
            1,
            0,
            0,
            0,
            0,
            0,
            1,
            0,
            1,
            0,
            1,
            0,
            1,
            0,
            2,
            0,
            2,
            1,
            0,
            0,
            0,
            1,
            0,
            1,
            0,
            0,
            1,
            0,
            1,
            0,
            1,
            0,
            2,
            0,
            0,
            0,
            1,
            1,
            0,
            0,
            1,
            0,
            0,
            0,
            2,
            0,
            1,
            0,
            0,
            0,
            1,
            1,
            0,
            0,
            0,
            0,
            0,
            0
        ],
        [
            1,
            0,
            0,
            0,
            1,
            0,
            1,
            0,
            0,
            0,
            0,
            0,
            0,
            0,
            2,
            0,
            0,
            2,
            1,
            0,
            1,
            0,
            1,
            0,
            0,
            1,
            0,
            1,
            0,
            0,
            0,
            0,
            0,
            0,
            0,
            1,
            0,
            1,
            1,
            0,
            1,
            1,
            1,
            0,
            1,
            1,
            1,
            0,
            1,
            0,
            1,
            0,
            0,
            0,
            0,
            1,
            0,
            1,
            0,
            1,
            0,
            0,
            1,
            1,
            1,
            0,
            0,
            1,
            1,
            0,
            1,
            0,
            2,
            0,
            0,
            0,
            1,
            1,
            0,
            0,
            0,
            1,
            0,
            1,
            0,
            0,
            0,
            0,
            0,
            0,
            1,
            1,
            0,
            0,
            0,
            0,
            1,
            1,
            1,
            1,
            0,
            0,
            0,
            0,
            0,
            0,
            0,
            1,
            0,
            0,
            1,
            0,
            0,
            0,
            1,
            0,
            0,
            1,
            0,
            0,
            0,
            0,
            1,
            1,
            0,
            0,
            1,
            0,
            0,
            1,
            0,
            0,
            0,
            1,
            0,
            0,
            0,
            0,
            0,
            0,
            0,
            0,
            0,
            0,
            0,
            1,
            0,
            1,
            0,
            0,
            1,
            0,
            0,
            1,
            0,
            0,
            0,
            1,
            1,
            0,
            0,
            1,
            0,
            0,
            0,
            1,
            1,
            0,
            0,
            0,
            1,
            0,
            1,
            1,
            1,
            1,
            1,
            0,
            0,
            0,
            0,
            0,
            0,
            0,
            0,
            0,
            1,
            0,
            0,
            0,
            1,
            0,
            0,
            0,
            0,
            0,
            0,
            0,
            1,
            0,
            0,
            0,
            0,
            0,
            1,
            0,
            1,
            0,
            1,
            1,
            0,
            0,
            1,
            1,
            1,
            0,
            1,
            0,
            1,
            0,
            0,
            1,
            1,
            0,
            0,
            0,
            2,
            0,
            0,
            1,
            0,
            1,
            0,
            0,
            0,
            1,
            0,
            0,
            0,
            1,
            0,
            0,
            1,
            1,
            0,
            1,
            0,
            1,
            0,
            1,
            0,
            0,
            1,
            0,
            0,
            0,
            1,
            0,
            0,
            0,
            1
        ],
        [
            1,
            0,
            0,
            0,
            0,
            1,
            0,
            2,
            0,
            0,
            0,
            1,
            0,
            0,
            0,
            0,
            1,
            0,
            0,
            0,
            1,
            1,
            0,
            2,
            1,
            0,
            0,
            0,
            0,
            1,
            1,
            0,
            1,
            0,
            0,
            1,
            0,
            0,
            1,
            1,
            1,
            0,
            1,
            0,
            0,
            0,
            1,
            0,
            0,
            0,
            0,
            1,
            0,
            0,
            1,
            0,
            0,
            0,
            0,
            0,
            0,
            0,
            0,
            0,
            1,
            0,
            0,
            0,
            0,
            1,
            0,
            0,
            0,
            0,
            0,
            0,
            0,
            0,
            0,
            0,
            0,
            0,
            0,
            1,
            0,
            1,
            0,
            0,
            1,
            0,
            0,
            1,
            1,
            0,
            1,
            1,
            0,
            1,
            0,
            0,
            0,
            0,
            0,
            0,
            1,
            0,
            0,
            1,
            1,
            1,
            1,
            0,
            0,
            0,
            1,
            0,
            1,
            1,
            0,
            0,
            1,
            1,
            0,
            0,
            1,
            0,
            1,
            1,
            0,
            0,
            0,
            1,
            0,
            1,
            1,
            0,
            0,
            1,
            0,
            0,
            1,
            0,
            1,
            0,
            1,
            0,
            1,
            0,
            0,
            1,
            0,
            0,
            0,
            0,
            0,
            0,
            1,
            0,
            1,
            0,
            0,
            0,
            1,
            1,
            0,
            1,
            0,
            0,
            0,
            0,
            2,
            0,
            0,
            1,
            0,
            0,
            0,
            0,
            1,
            1,
            1,
            0,
            0,
            0,
            0,
            1,
            1,
            0,
            1,
            1,
            0,
            0,
            0,
            1,
            0,
            1,
            0,
            0,
            0,
            1,
            1,
            1,
            0,
            0,
            1,
            0,
            0,
            0,
            1,
            1,
            1,
            1,
            0,
            1,
            1,
            0,
            1,
            1,
            0,
            0,
            0,
            0,
            0,
            0,
            1,
            0,
            0,
            0,
            1,
            0,
            1,
            2,
            1,
            0,
            0,
            1,
            0,
            0,
            0,
            1,
            1,
            0,
            0,
            0,
            0,
            0,
            1,
            1,
            0,
            0,
            2,
            1,
            0,
            0,
            0,
            0,
            1,
            0,
            1,
            1,
            0
        ],
        [
            0,
            0,
            0,
            1,
            1,
            0,
            1,
            0,
            0,
            1,
            0,
            1,
            0,
            0,
            0,
            0,
            0,
            0,
            0,
            1,
            0,
            0,
            0,
            0,
            0,
            0,
            0,
            1,
            0,
            1,
            0,
            1,
            0,
            0,
            0,
            0,
            0,
            1,
            0,
            0,
            0,
            0,
            0,
            1,
            0,
            0,
            1,
            0,
            1,
            0,
            0,
            1,
            0,
            0,
            1,
            0,
            0,
            0,
            0,
            0,
            1,
            0,
            0,
            0,
            0,
            0,
            0,
            1,
            0,
            0,
            0,
            1,
            0,
            0,
            0,
            0,
            0,
            1,
            0,
            1,
            0,
            0,
            1,
            1,
            1,
            1,
            0,
            0,
            1,
            0,
            0,
            1,
            1,
            0,
            0,
            0,
            1,
            0,
            0,
            0,
            1,
            0,
            0,
            0,
            0,
            1,
            1,
            0,
            1,
            2,
            1,
            0,
            0,
            0,
            1,
            0,
            0,
            1,
            1,
            0,
            0,
            1,
            1,
            0,
            0,
            0,
            0,
            0,
            1,
            0,
            0,
            0,
            0,
            0,
            0,
            0,
            0,
            0,
            0,
            0,
            0,
            1,
            1,
            1,
            1,
            0,
            0,
            1,
            1,
            0,
            0,
            0,
            0,
            1,
            0,
            0,
            0,
            0,
            0,
            0,
            0,
            0,
            0,
            1,
            0,
            0,
            1,
            0,
            0,
            0,
            0,
            1,
            0,
            0,
            0,
            0,
            0,
            0,
            0,
            0,
            0,
            0,
            0,
            1,
            0,
            0,
            1,
            1,
            1,
            1,
            1,
            0,
            0,
            0,
            1,
            1,
            1,
            0,
            0,
            1,
            1,
            0,
            1,
            0,
            1,
            0,
            0,
            0,
            1,
            0,
            1,
            0,
            0,
            1,
            0,
            0,
            0,
            0,
            1,
            1,
            0,
            0,
            0,
            0,
            1,
            0,
            0,
            0,
            1,
            0,
            0,
            0,
            0,
            0,
            0,
            0,
            0,
            0,
            0,
            1,
            0,
            1,
            0,
            0,
            1,
            0,
            0,
            1,
            1,
            0,
            1,
            1,
            1,
            1,
            0,
            1,
            0,
            0,
            0,
            0,
            0
        ],
        [
            1,
            0,
            1,
            1,
            0,
            0,
            1,
            1,
            0,
            0,
            0,
            1,
            1,
            1,
            0,
            0,
            0,
            1,
            1,
            0,
            0,
            0,
            0,
            0,
            0,
            0,
            0,
            2,
            0,
            1,
            1,
            0,
            0,
            0,
            0,
            0,
            0,
            1,
            0,
            1,
            0,
            0,
            0,
            0,
            0,
            0,
            1,
            0,
            0,
            0,
            1,
            0,
            0,
            0,
            0,
            0,
            0,
            0,
            0,
            0,
            0,
            1,
            0,
            0,
            0,
            2,
            1,
            0,
            0,
            0,
            1,
            0,
            0,
            0,
            0,
            1,
            0,
            0,
            1,
            0,
            0,
            0,
            1,
            1,
            0,
            0,
            1,
            1,
            1,
            0,
            1,
            1,
            0,
            1,
            0,
            1,
            0,
            1,
            1,
            1,
            1,
            1,
            1,
            0,
            0,
            1,
            1,
            1,
            1,
            1,
            0,
            0,
            0,
            1,
            0,
            0,
            0,
            0,
            1,
            1,
            0,
            0,
            1,
            1,
            1,
            0,
            0,
            1,
            0,
            0,
            1,
            1,
            1,
            0,
            0,
            0,
            0,
            0,
            0,
            0,
            0,
            0,
            1,
            1,
            1,
            0,
            0,
            0,
            0,
            0,
            0,
            0,
            0,
            0,
            1,
            0,
            1,
            0,
            0,
            1,
            1,
            0,
            1,
            1,
            1,
            0,
            0,
            1,
            1,
            0,
            0,
            0,
            0,
            0,
            0,
            1,
            0,
            0,
            0,
            1,
            1,
            0,
            0,
            0,
            0,
            0,
            0,
            1,
            0,
            0,
            1,
            0,
            0,
            0,
            1,
            1,
            0,
            0,
            1,
            0,
            1,
            0,
            0,
            0,
            0,
            0,
            0,
            0,
            1,
            1,
            1,
            0,
            0,
            0,
            0,
            0,
            0,
            1,
            1,
            0,
            0,
            1,
            0,
            0,
            0,
            0,
            0,
            0,
            1,
            0,
            1,
            1,
            1,
            0,
            0,
            0,
            0,
            0,
            0,
            1,
            0,
            1,
            0,
            1,
            0,
            0,
            1,
            0,
            0,
            1,
            0,
            0,
            0,
            0,
            0,
            1,
            2,
            0,
            0,
            0,
            1
        ],
        [
            0,
            0,
            0,
            0,
            0,
            0,
            0,
            0,
            1,
            0,
            0,
            0,
            1,
            0,
            1,
            0,
            0,
            0,
            0,
            0,
            0,
            1,
            0,
            0,
            1,
            1,
            0,
            1,
            1,
            0,
            1,
            0,
            1,
            1,
            1,
            0,
            0,
            0,
            0,
            0,
            1,
            0,
            0,
            0,
            0,
            0,
            0,
            0,
            0,
            1,
            1,
            1,
            1,
            0,
            0,
            0,
            0,
            0,
            0,
            0,
            0,
            0,
            0,
            1,
            0,
            1,
            0,
            0,
            1,
            0,
            0,
            1,
            1,
            0,
            0,
            1,
            1,
            1,
            0,
            1,
            0,
            1,
            0,
            0,
            1,
            0,
            0,
            0,
            0,
            0,
            0,
            0,
            1,
            0,
            1,
            0,
            1,
            1,
            1,
            0,
            0,
            0,
            0,
            1,
            0,
            0,
            0,
            1,
            1,
            0,
            0,
            0,
            0,
            0,
            0,
            1,
            1,
            1,
            1,
            0,
            1,
            0,
            0,
            0,
            0,
            0,
            0,
            0,
            1,
            1,
            0,
            0,
            0,
            0,
            1,
            0,
            1,
            0,
            1,
            0,
            0,
            0,
            1,
            0,
            0,
            0,
            0,
            0,
            0,
            1,
            0,
            0,
            0,
            0,
            1,
            0,
            1,
            0,
            0,
            1,
            1,
            1,
            0,
            1,
            1,
            0,
            0,
            0,
            1,
            1,
            1,
            1,
            1,
            1,
            1,
            0,
            0,
            0,
            1,
            0,
            0,
            0,
            0,
            0,
            0,
            0,
            0,
            0,
            0,
            0,
            0,
            0,
            1,
            1,
            1,
            1,
            1,
            0,
            1,
            0,
            0,
            0,
            0,
            1,
            1,
            1,
            0,
            1,
            1,
            1,
            1,
            0,
            1,
            0,
            0,
            0,
            1,
            0,
            0,
            1,
            0,
            0,
            1,
            0,
            0,
            1,
            1,
            0,
            0,
            1,
            0,
            0,
            0,
            0,
            0,
            0,
            0,
            1,
            0,
            1,
            0,
            0,
            0,
            1,
            0,
            1,
            0,
            1,
            0,
            1,
            1,
            1,
            0,
            1,
            0,
            1,
            0,
            0,
            0,
            0,
            0
        ],
        [
            0,
            0,
            1,
            1,
            0,
            1,
            1,
            1,
            0,
            1,
            1,
            2,
            0,
            0,
            1,
            1,
            0,
            0,
            0,
            1,
            1,
            1,
            1,
            1,
            0,
            1,
            0,
            1,
            0,
            0,
            2,
            0,
            2,
            1,
            0,
            1,
            0,
            1,
            0,
            1,
            1,
            0,
            0,
            1,
            0,
            0,
            0,
            1,
            0,
            0,
            0,
            0,
            0,
            1,
            0,
            0,
            1,
            0,
            0,
            0,
            0,
            0,
            0,
            1,
            1,
            0,
            0,
            0,
            0,
            1,
            1,
            1,
            1,
            0,
            0,
            1,
            0,
            0,
            1,
            0,
            0,
            0,
            1,
            0,
            0,
            0,
            1,
            1,
            0,
            0,
            0,
            0,
            0,
            0,
            0,
            1,
            0,
            1,
            0,
            1,
            1,
            1,
            2,
            1,
            0,
            1,
            1,
            0,
            0,
            1,
            0,
            0,
            1,
            0,
            1,
            0,
            0,
            0,
            0,
            1,
            1,
            0,
            0,
            0,
            0,
            0,
            1,
            0,
            0,
            1,
            1,
            0,
            1,
            0,
            0,
            2,
            0,
            1,
            0,
            0,
            0,
            0,
            0,
            0,
            1,
            0,
            1,
            1,
            0,
            0,
            0,
            0,
            0,
            0,
            0,
            1,
            0,
            0,
            0,
            0,
            0,
            0,
            0,
            1,
            1,
            0,
            1,
            0,
            0,
            1,
            0,
            1,
            0,
            0,
            0,
            1,
            0,
            0,
            1,
            0,
            0,
            0,
            1,
            0,
            1,
            0,
            0,
            0,
            0,
            0,
            0,
            0,
            1,
            1,
            0,
            1,
            0,
            0,
            0,
            0,
            1,
            1,
            0,
            0,
            1,
            1,
            0,
            0,
            0,
            0,
            1,
            1,
            1,
            0,
            1,
            0,
            0,
            1,
            0,
            0,
            0,
            0,
            0,
            0,
            1,
            1,
            1,
            0,
            1,
            1,
            0,
            0,
            1,
            1,
            0,
            0,
            1,
            0,
            1,
            1,
            1,
            0,
            1,
            0,
            0,
            1,
            0,
            0,
            1,
            0,
            0,
            0,
            0,
            0,
            0,
            0,
            1,
            1,
            0,
            0
        ],
        [
            0,
            0,
            0,
            0,
            0,
            0,
            1,
            1,
            0,
            0,
            0,
            0,
            0,
            1,
            0,
            1,
            0,
            1,
            0,
            1,
            0,
            0,
            0,
            0,
            1,
            1,
            0,
            2,
            0,
            0,
            1,
            0,
            0,
            1,
            0,
            1,
            0,
            0,
            1,
            1,
            1,
            0,
            1,
            0,
            1,
            0,
            0,
            1,
            0,
            0,
            0,
            1,
            1,
            0,
            1,
            0,
            0,
            0,
            0,
            1,
            0,
            0,
            0,
            1,
            0,
            0,
            0,
            0,
            0,
            0,
            1,
            0,
            0,
            0,
            1,
            0,
            0,
            0,
            0,
            1,
            0,
            0,
            0,
            0,
            0,
            0,
            0,
            0,
            1,
            1,
            1,
            1,
            0,
            1,
            0,
            0,
            0,
            1,
            0,
            1,
            0,
            0,
            1,
            1,
            1,
            0,
            1,
            0,
            0,
            0,
            1,
            0,
            1,
            1,
            1,
            1,
            0,
            1,
            0,
            0,
            1,
            0,
            1,
            1,
            0,
            0,
            1,
            0,
            0,
            0,
            0,
            0,
            0,
            1,
            0,
            0,
            0,
            1,
            0,
            1,
            0,
            0,
            0,
            0,
            1,
            1,
            0,
            0,
            1,
            0,
            0,
            1,
            0,
            0,
            1,
            0,
            0,
            2,
            0,
            0,
            0,
            1,
            1,
            0,
            0,
            2,
            0,
            0,
            1,
            1,
            0,
            0,
            0,
            0,
            1,
            1,
            1,
            0,
            1,
            0,
            0,
            0,
            0,
            1,
            0,
            0,
            1,
            1,
            0,
            0,
            1,
            0,
            1,
            0,
            1,
            1,
            1,
            0,
            1,
            1,
            0,
            0,
            0,
            1,
            0,
            1,
            1,
            1,
            0,
            0,
            1,
            1,
            0,
            0,
            0,
            0,
            1,
            0,
            0,
            0,
            0,
            2,
            1,
            1,
            1,
            0,
            1,
            0,
            0,
            0,
            0,
            0,
            1,
            0,
            0,
            1,
            0,
            0,
            0,
            0,
            0,
            0,
            0,
            0,
            1,
            0,
            0,
            0,
            0,
            1,
            0,
            0,
            0,
            0,
            0,
            0,
            1,
            1,
            0,
            1
        ],
        [
            0,
            0,
            0,
            1,
            0,
            1,
            0,
            1,
            1,
            0,
            0,
            0,
            0,
            0,
            0,
            0,
            1,
            1,
            0,
            0,
            0,
            1,
            0,
            0,
            1,
            0,
            1,
            0,
            0,
            0,
            1,
            0,
            0,
            0,
            0,
            0,
            0,
            1,
            0,
            1,
            1,
            1,
            0,
            0,
            0,
            0,
            0,
            1,
            0,
            0,
            0,
            0,
            0,
            0,
            1,
            1,
            0,
            1,
            0,
            0,
            0,
            0,
            0,
            0,
            0,
            0,
            0,
            0,
            0,
            0,
            1,
            1,
            0,
            1,
            1,
            1,
            0,
            0,
            1,
            0,
            0,
            0,
            1,
            0,
            0,
            0,
            2,
            0,
            0,
            0,
            0,
            0,
            1,
            1,
            0,
            0,
            0,
            0,
            0,
            0,
            0,
            0,
            1,
            1,
            1,
            0,
            0,
            1,
            1,
            0,
            0,
            1,
            1,
            0,
            0,
            2,
            0,
            0,
            0,
            1,
            0,
            0,
            0,
            0,
            0,
            0,
            1,
            0,
            0,
            1,
            0,
            1,
            1,
            1,
            0,
            0,
            0,
            0,
            1,
            0,
            0,
            0,
            0,
            1,
            1,
            0,
            0,
            1,
            1,
            0,
            1,
            1,
            1,
            0,
            0,
            0,
            0,
            0,
            0,
            1,
            0,
            0,
            0,
            0,
            1,
            0,
            0,
            0,
            1,
            0,
            0,
            0,
            0,
            1,
            0,
            1,
            1,
            0,
            0,
            0,
            1,
            0,
            0,
            1,
            0,
            0,
            0,
            1,
            0,
            1,
            0,
            1,
            1,
            0,
            0,
            0,
            1,
            0,
            0,
            0,
            1,
            0,
            0,
            0,
            0,
            0,
            0,
            1,
            1,
            0,
            0,
            1,
            0,
            0,
            0,
            1,
            1,
            0,
            0,
            1,
            1,
            0,
            0,
            0,
            0,
            0,
            0,
            1,
            0,
            1,
            1,
            1,
            0,
            1,
            0,
            1,
            0,
            0,
            1,
            1,
            0,
            1,
            0,
            0,
            0,
            1,
            0,
            1,
            1,
            1,
            0,
            0,
            0,
            1,
            0,
            0,
            1,
            0,
            1,
            0
        ]
    ],
    "recall_bad": 0.9060606060606059,
    "recall_bad_list": [
        0.8068181818181818,
        0.9204545454545454,
        0.9310344827586207,
        0.9080459770114943,
        0.8275862068965517,
        0.9310344827586207,
        0.9195402298850575,
        0.9655172413793104,
        0.9425287356321839,
        0.9080459770114943
    ],
    "recall_good": 0.9708615102845872,
    "recall_good_list": [
        0.9881656804733728,
        0.9644970414201184,
        0.9702380952380952,
        0.9583333333333334,
        0.9940476190476191,
        0.9761904761904762,
        0.9583333333333334,
        0.9464285714285714,
        0.9642857142857143,
        0.9880952380952381
    ],
    "recall_ugly": 0.3733333333333334,
    "recall_ugly_list": [
        0.0,
        1.0,
        0.6666666666666666,
        0.3333333333333333,
        0.0,
        0.3333333333333333,
        0.0,
        0.6,
        0.6,
        0.2
    ],
    "target": [
        [
            1,
            0,
            0,
            1,
            0,
            0,
            1,
            0,
            1,
            2,
            1,
            0,
            1,
            0,
            1,
            1,
            1,
            0,
            1,
            0,
            0,
            0,
            0,
            1,
            0,
            0,
            0,
            1,
            0,
            0,
            0,
            1,
            0,
            0,
            0,
            0,
            0,
            1,
            1,
            0,
            0,
            0,
            0,
            0,
            0,
            0,
            1,
            1,
            0,
            0,
            0,
            1,
            1,
            0,
            0,
            0,
            0,
            0,
            1,
            0,
            0,
            1,
            0,
            0,
            1,
            0,
            1,
            1,
            0,
            0,
            0,
            0,
            0,
            1,
            1,
            0,
            0,
            1,
            0,
            1,
            0,
            0,
            0,
            0,
            1,
            1,
            1,
            0,
            0,
            0,
            0,
            1,
            0,
            1,
            1,
            1,
            0,
            0,
            0,
            0,
            1,
            0,
            1,
            1,
            0,
            1,
            0,
            0,
            0,
            1,
            0,
            1,
            0,
            0,
            0,
            0,
            0,
            0,
            0,
            1,
            0,
            1,
            0,
            2,
            0,
            1,
            0,
            1,
            1,
            0,
            0,
            0,
            0,
            1,
            0,
            2,
            0,
            0,
            1,
            1,
            2,
            0,
            1,
            1,
            0,
            0,
            0,
            1,
            0,
            1,
            1,
            0,
            0,
            1,
            1,
            0,
            0,
            0,
            0,
            0,
            1,
            2,
            0,
            0,
            0,
            0,
            0,
            0,
            0,
            0,
            0,
            0,
            0,
            0,
            0,
            0,
            2,
            1,
            1,
            0,
            1,
            0,
            1,
            0,
            0,
            0,
            1,
            1,
            0,
            1,
            0,
            0,
            1,
            1,
            0,
            0,
            0,
            0,
            1,
            1,
            1,
            0,
            0,
            1,
            0,
            0,
            0,
            1,
            0,
            1,
            0,
            0,
            0,
            0,
            0,
            1,
            1,
            0,
            1,
            0,
            0,
            1,
            1,
            1,
            0,
            0,
            0,
            0,
            0,
            0,
            1,
            0,
            1,
            0,
            0,
            1,
            0,
            1,
            0,
            0,
            0,
            1,
            0,
            0,
            1,
            0,
            0,
            0,
            1,
            0,
            0,
            0,
            0,
            0,
            1,
            0,
            0,
            0,
            0,
            0,
            0,
            1,
            1
        ],
        [
            0,
            0,
            0,
            0,
            0,
            1,
            0,
            0,
            0,
            0,
            1,
            1,
            1,
            1,
            0,
            0,
            1,
            1,
            0,
            0,
            1,
            0,
            1,
            1,
            1,
            0,
            0,
            0,
            0,
            0,
            1,
            1,
            0,
            0,
            0,
            1,
            0,
            1,
            0,
            0,
            1,
            0,
            1,
            0,
            1,
            0,
            0,
            0,
            1,
            0,
            0,
            0,
            0,
            0,
            0,
            1,
            0,
            0,
            1,
            0,
            0,
            0,
            0,
            0,
            1,
            0,
            0,
            1,
            0,
            0,
            1,
            0,
            0,
            0,
            0,
            0,
            1,
            0,
            0,
            0,
            0,
            0,
            0,
            0,
            0,
            0,
            0,
            0,
            0,
            1,
            0,
            0,
            1,
            1,
            1,
            1,
            0,
            0,
            0,
            1,
            0,
            1,
            1,
            1,
            0,
            1,
            0,
            0,
            0,
            0,
            0,
            1,
            1,
            0,
            1,
            0,
            0,
            2,
            2,
            0,
            1,
            0,
            0,
            0,
            1,
            1,
            0,
            0,
            1,
            0,
            0,
            1,
            0,
            1,
            1,
            0,
            0,
            0,
            1,
            1,
            0,
            0,
            0,
            0,
            0,
            0,
            0,
            1,
            2,
            1,
            0,
            0,
            0,
            0,
            1,
            0,
            0,
            1,
            0,
            1,
            0,
            0,
            0,
            0,
            1,
            0,
            0,
            1,
            1,
            0,
            1,
            1,
            0,
            0,
            0,
            1,
            0,
            1,
            0,
            0,
            0,
            1,
            1,
            0,
            1,
            1,
            0,
            1,
            1,
            2,
            0,
            1,
            2,
            1,
            0,
            1,
            1,
            0,
            0,
            0,
            0,
            0,
            1,
            0,
            0,
            1,
            0,
            0,
            0,
            0,
            0,
            1,
            0,
            0,
            0,
            0,
            0,
            1,
            0,
            1,
            0,
            2,
            1,
            0,
            0,
            0,
            1,
            0,
            1,
            0,
            0,
            1,
            0,
            1,
            0,
            1,
            0,
            1,
            0,
            0,
            0,
            1,
            1,
            0,
            0,
            1,
            0,
            0,
            0,
            1,
            0,
            1,
            0,
            0,
            0,
            1,
            1,
            0,
            0,
            0,
            0,
            0,
            0
        ],
        [
            1,
            0,
            0,
            0,
            1,
            0,
            1,
            0,
            0,
            0,
            0,
            0,
            0,
            0,
            2,
            0,
            0,
            2,
            0,
            0,
            1,
            0,
            1,
            0,
            0,
            1,
            0,
            1,
            0,
            0,
            0,
            0,
            0,
            0,
            0,
            1,
            0,
            1,
            1,
            0,
            1,
            1,
            1,
            0,
            1,
            1,
            1,
            0,
            1,
            0,
            1,
            0,
            0,
            0,
            0,
            1,
            0,
            1,
            0,
            1,
            0,
            0,
            1,
            1,
            1,
            0,
            0,
            1,
            1,
            0,
            1,
            0,
            2,
            0,
            0,
            0,
            1,
            2,
            0,
            0,
            0,
            1,
            0,
            1,
            0,
            1,
            0,
            0,
            0,
            1,
            1,
            1,
            0,
            0,
            0,
            0,
            1,
            1,
            1,
            2,
            0,
            0,
            0,
            0,
            0,
            0,
            0,
            0,
            0,
            0,
            1,
            0,
            0,
            0,
            1,
            0,
            0,
            1,
            0,
            0,
            0,
            0,
            1,
            1,
            0,
            0,
            1,
            0,
            0,
            1,
            0,
            0,
            0,
            1,
            0,
            0,
            0,
            0,
            0,
            0,
            0,
            0,
            0,
            0,
            0,
            1,
            0,
            1,
            0,
            0,
            1,
            0,
            0,
            1,
            0,
            1,
            0,
            1,
            1,
            0,
            0,
            1,
            0,
            0,
            0,
            1,
            1,
            0,
            0,
            0,
            1,
            0,
            1,
            1,
            1,
            1,
            1,
            0,
            0,
            0,
            0,
            0,
            0,
            0,
            0,
            0,
            0,
            0,
            0,
            0,
            1,
            0,
            0,
            0,
            0,
            0,
            0,
            0,
            1,
            0,
            0,
            1,
            0,
            1,
            1,
            1,
            1,
            0,
            1,
            1,
            0,
            0,
            1,
            1,
            1,
            0,
            1,
            0,
            1,
            0,
            0,
            1,
            1,
            0,
            0,
            0,
            2,
            0,
            0,
            0,
            0,
            1,
            0,
            0,
            0,
            0,
            0,
            0,
            0,
            1,
            0,
            0,
            1,
            1,
            0,
            1,
            0,
            1,
            0,
            1,
            0,
            0,
            1,
            0,
            0,
            0,
            1,
            0,
            0,
            0,
            1
        ],
        [
            1,
            0,
            0,
            0,
            0,
            1,
            0,
            2,
            0,
            0,
            0,
            1,
            0,
            0,
            0,
            0,
            1,
            0,
            0,
            0,
            1,
            1,
            0,
            1,
            1,
            0,
            1,
            0,
            0,
            1,
            1,
            0,
            1,
            0,
            0,
            0,
            0,
            0,
            1,
            1,
            1,
            0,
            1,
            0,
            0,
            0,
            1,
            0,
            0,
            0,
            0,
            1,
            0,
            0,
            1,
            0,
            0,
            0,
            0,
            0,
            1,
            0,
            0,
            0,
            0,
            0,
            0,
            0,
            0,
            1,
            0,
            0,
            0,
            0,
            0,
            0,
            0,
            0,
            0,
            0,
            0,
            1,
            0,
            1,
            0,
            1,
            0,
            0,
            1,
            0,
            0,
            1,
            1,
            0,
            1,
            1,
            0,
            1,
            0,
            0,
            0,
            0,
            0,
            0,
            1,
            0,
            0,
            1,
            1,
            0,
            1,
            0,
            0,
            0,
            1,
            0,
            1,
            1,
            0,
            0,
            1,
            0,
            0,
            0,
            1,
            0,
            1,
            1,
            0,
            0,
            0,
            1,
            0,
            1,
            1,
            0,
            0,
            1,
            0,
            0,
            1,
            0,
            1,
            0,
            1,
            0,
            1,
            0,
            0,
            1,
            0,
            0,
            0,
            0,
            0,
            0,
            1,
            0,
            2,
            0,
            0,
            0,
            1,
            2,
            0,
            0,
            0,
            0,
            0,
            0,
            1,
            0,
            0,
            1,
            0,
            0,
            0,
            0,
            1,
            1,
            1,
            0,
            0,
            0,
            0,
            1,
            1,
            0,
            1,
            1,
            0,
            0,
            0,
            1,
            0,
            1,
            1,
            0,
            0,
            1,
            1,
            2,
            0,
            0,
            1,
            0,
            0,
            0,
            1,
            1,
            2,
            1,
            0,
            1,
            1,
            0,
            1,
            1,
            0,
            0,
            0,
            0,
            0,
            0,
            1,
            0,
            0,
            0,
            1,
            0,
            1,
            1,
            1,
            0,
            0,
            1,
            0,
            0,
            0,
            1,
            1,
            0,
            0,
            0,
            0,
            1,
            0,
            1,
            0,
            0,
            2,
            1,
            0,
            0,
            0,
            0,
            0,
            0,
            1,
            1,
            0
        ],
        [
            0,
            0,
            0,
            1,
            1,
            0,
            2,
            0,
            0,
            2,
            0,
            1,
            0,
            0,
            0,
            0,
            0,
            0,
            1,
            1,
            0,
            1,
            0,
            0,
            0,
            0,
            0,
            1,
            0,
            2,
            0,
            1,
            0,
            0,
            0,
            0,
            0,
            1,
            0,
            1,
            0,
            0,
            0,
            1,
            0,
            0,
            1,
            0,
            1,
            0,
            0,
            1,
            0,
            1,
            1,
            0,
            0,
            0,
            0,
            0,
            1,
            0,
            0,
            0,
            0,
            0,
            0,
            1,
            0,
            1,
            0,
            1,
            0,
            0,
            0,
            0,
            0,
            1,
            0,
            1,
            1,
            0,
            1,
            1,
            1,
            1,
            0,
            0,
            1,
            0,
            0,
            1,
            1,
            1,
            0,
            0,
            1,
            0,
            0,
            0,
            1,
            0,
            0,
            1,
            0,
            1,
            0,
            0,
            1,
            1,
            1,
            1,
            1,
            0,
            1,
            0,
            0,
            1,
            1,
            0,
            0,
            1,
            1,
            0,
            0,
            0,
            0,
            0,
            1,
            0,
            0,
            0,
            0,
            0,
            0,
            0,
            0,
            1,
            0,
            0,
            0,
            1,
            1,
            1,
            1,
            0,
            0,
            1,
            2,
            0,
            0,
            0,
            0,
            1,
            0,
            0,
            0,
            0,
            0,
            0,
            0,
            0,
            0,
            1,
            0,
            1,
            1,
            0,
            0,
            0,
            0,
            1,
            0,
            0,
            0,
            0,
            0,
            0,
            0,
            0,
            0,
            0,
            0,
            1,
            0,
            0,
            1,
            2,
            1,
            2,
            1,
            0,
            0,
            0,
            1,
            1,
            1,
            0,
            0,
            1,
            1,
            0,
            1,
            0,
            1,
            0,
            0,
            0,
            1,
            0,
            1,
            0,
            0,
            1,
            1,
            0,
            0,
            0,
            1,
            1,
            0,
            0,
            0,
            0,
            1,
            0,
            0,
            0,
            1,
            0,
            0,
            0,
            0,
            0,
            0,
            0,
            0,
            0,
            0,
            1,
            0,
            1,
            0,
            0,
            1,
            0,
            0,
            1,
            1,
            0,
            1,
            1,
            1,
            1,
            0,
            1,
            0,
            0,
            0,
            1,
            0
        ],
        [
            1,
            1,
            1,
            1,
            0,
            0,
            1,
            1,
            0,
            0,
            0,
            1,
            1,
            1,
            0,
            0,
            0,
            1,
            1,
            0,
            0,
            0,
            0,
            0,
            0,
            1,
            0,
            2,
            0,
            1,
            2,
            0,
            0,
            0,
            0,
            0,
            0,
            1,
            0,
            1,
            0,
            0,
            0,
            0,
            0,
            0,
            1,
            0,
            0,
            0,
            1,
            0,
            0,
            0,
            0,
            0,
            0,
            0,
            0,
            0,
            0,
            1,
            0,
            0,
            0,
            2,
            1,
            0,
            0,
            0,
            1,
            0,
            0,
            0,
            0,
            1,
            0,
            0,
            1,
            0,
            0,
            0,
            1,
            0,
            0,
            0,
            1,
            1,
            1,
            0,
            1,
            0,
            0,
            1,
            0,
            1,
            0,
            1,
            1,
            2,
            1,
            1,
            1,
            0,
            0,
            1,
            1,
            1,
            1,
            1,
            0,
            0,
            0,
            1,
            0,
            0,
            0,
            0,
            2,
            1,
            0,
            0,
            1,
            1,
            1,
            0,
            0,
            1,
            0,
            0,
            1,
            1,
            1,
            0,
            0,
            0,
            0,
            0,
            0,
            1,
            0,
            0,
            1,
            1,
            1,
            0,
            0,
            0,
            0,
            0,
            0,
            0,
            0,
            0,
            1,
            0,
            1,
            0,
            0,
            1,
            1,
            0,
            1,
            1,
            1,
            0,
            0,
            2,
            1,
            0,
            0,
            0,
            0,
            0,
            0,
            1,
            0,
            0,
            0,
            1,
            1,
            0,
            0,
            0,
            0,
            0,
            0,
            1,
            0,
            0,
            0,
            0,
            0,
            0,
            1,
            1,
            0,
            1,
            1,
            0,
            1,
            0,
            0,
            0,
            0,
            0,
            0,
            1,
            1,
            1,
            0,
            0,
            0,
            0,
            0,
            0,
            0,
            1,
            1,
            0,
            0,
            1,
            0,
            0,
            0,
            0,
            0,
            0,
            1,
            0,
            1,
            1,
            1,
            0,
            0,
            0,
            0,
            0,
            0,
            1,
            0,
            1,
            0,
            1,
            0,
            0,
            1,
            0,
            0,
            1,
            0,
            0,
            0,
            0,
            0,
            1,
            1,
            0,
            0,
            0,
            1
        ],
        [
            0,
            0,
            0,
            0,
            0,
            0,
            0,
            0,
            1,
            0,
            0,
            1,
            1,
            0,
            1,
            0,
            0,
            0,
            0,
            0,
            0,
            1,
            0,
            0,
            1,
            1,
            0,
            1,
            1,
            1,
            2,
            0,
            1,
            1,
            1,
            0,
            0,
            0,
            0,
            1,
            1,
            0,
            0,
            0,
            0,
            0,
            0,
            0,
            0,
            1,
            1,
            1,
            1,
            0,
            0,
            0,
            0,
            1,
            0,
            0,
            0,
            0,
            0,
            0,
            0,
            1,
            0,
            0,
            1,
            0,
            0,
            1,
            1,
            0,
            0,
            0,
            1,
            1,
            0,
            1,
            0,
            1,
            0,
            0,
            1,
            0,
            0,
            0,
            0,
            0,
            0,
            0,
            1,
            0,
            1,
            0,
            2,
            1,
            1,
            0,
            0,
            0,
            0,
            1,
            0,
            0,
            0,
            1,
            1,
            0,
            0,
            0,
            1,
            0,
            0,
            1,
            1,
            1,
            1,
            0,
            1,
            0,
            0,
            0,
            0,
            0,
            0,
            0,
            1,
            1,
            0,
            0,
            0,
            0,
            0,
            0,
            1,
            0,
            1,
            0,
            0,
            0,
            1,
            0,
            0,
            0,
            0,
            0,
            0,
            1,
            0,
            0,
            0,
            0,
            1,
            1,
            1,
            0,
            0,
            1,
            1,
            1,
            0,
            1,
            1,
            0,
            0,
            0,
            1,
            1,
            1,
            0,
            0,
            1,
            1,
            0,
            0,
            0,
            1,
            0,
            0,
            0,
            0,
            0,
            0,
            0,
            0,
            0,
            0,
            0,
            0,
            0,
            1,
            2,
            1,
            1,
            1,
            0,
            1,
            0,
            0,
            0,
            0,
            1,
            1,
            1,
            0,
            1,
            1,
            1,
            1,
            0,
            1,
            0,
            0,
            0,
            1,
            0,
            0,
            1,
            0,
            0,
            1,
            0,
            0,
            1,
            1,
            0,
            0,
            2,
            0,
            0,
            0,
            1,
            0,
            0,
            0,
            1,
            0,
            1,
            0,
            0,
            0,
            0,
            0,
            2,
            0,
            1,
            0,
            1,
            0,
            2,
            0,
            1,
            0,
            1,
            0,
            0,
            0,
            0,
            0
        ],
        [
            0,
            0,
            1,
            1,
            0,
            1,
            1,
            1,
            0,
            1,
            1,
            2,
            0,
            0,
            1,
            1,
            0,
            0,
            0,
            1,
            1,
            1,
            1,
            1,
            0,
            1,
            0,
            1,
            0,
            0,
            1,
            0,
            2,
            1,
            0,
            0,
            0,
            1,
            0,
            1,
            1,
            0,
            0,
            1,
            0,
            0,
            0,
            1,
            0,
            0,
            0,
            0,
            0,
            1,
            0,
            0,
            1,
            0,
            0,
            0,
            0,
            0,
            0,
            0,
            1,
            0,
            0,
            0,
            0,
            1,
            1,
            1,
            0,
            0,
            0,
            1,
            0,
            0,
            1,
            0,
            0,
            0,
            1,
            0,
            0,
            0,
            1,
            1,
            0,
            0,
            0,
            0,
            0,
            0,
            0,
            1,
            0,
            1,
            0,
            1,
            0,
            1,
            2,
            1,
            0,
            1,
            0,
            0,
            0,
            1,
            0,
            0,
            1,
            1,
            1,
            0,
            0,
            0,
            0,
            1,
            1,
            0,
            0,
            0,
            0,
            0,
            1,
            0,
            0,
            1,
            1,
            0,
            1,
            0,
            0,
            1,
            0,
            1,
            0,
            0,
            0,
            0,
            0,
            0,
            1,
            0,
            1,
            0,
            0,
            0,
            0,
            0,
            0,
            0,
            0,
            1,
            0,
            0,
            0,
            0,
            0,
            0,
            0,
            1,
            1,
            0,
            1,
            0,
            0,
            2,
            0,
            1,
            0,
            0,
            0,
            1,
            0,
            0,
            1,
            0,
            0,
            0,
            1,
            0,
            1,
            0,
            0,
            0,
            0,
            0,
            0,
            0,
            1,
            1,
            0,
            1,
            0,
            0,
            0,
            0,
            2,
            1,
            0,
            0,
            1,
            1,
            0,
            0,
            0,
            0,
            1,
            1,
            0,
            0,
            1,
            0,
            0,
            1,
            0,
            0,
            0,
            0,
            0,
            0,
            1,
            1,
            1,
            0,
            0,
            1,
            0,
            0,
            1,
            1,
            0,
            0,
            1,
            0,
            1,
            1,
            1,
            0,
            1,
            0,
            0,
            1,
            0,
            0,
            1,
            0,
            0,
            0,
            0,
            0,
            0,
            0,
            1,
            0,
            0,
            0
        ],
        [
            0,
            0,
            0,
            0,
            0,
            0,
            1,
            1,
            0,
            0,
            0,
            0,
            0,
            1,
            0,
            1,
            0,
            1,
            0,
            1,
            0,
            0,
            0,
            0,
            1,
            1,
            0,
            2,
            0,
            0,
            1,
            0,
            0,
            1,
            0,
            1,
            0,
            0,
            1,
            0,
            1,
            0,
            1,
            0,
            1,
            0,
            0,
            1,
            0,
            0,
            0,
            1,
            2,
            0,
            1,
            0,
            0,
            0,
            0,
            1,
            0,
            0,
            0,
            1,
            0,
            0,
            0,
            0,
            0,
            0,
            1,
            0,
            0,
            0,
            1,
            0,
            0,
            0,
            0,
            0,
            0,
            1,
            0,
            0,
            0,
            0,
            0,
            0,
            1,
            1,
            1,
            1,
            0,
            1,
            0,
            0,
            0,
            1,
            0,
            1,
            0,
            0,
            1,
            1,
            0,
            0,
            1,
            0,
            0,
            0,
            1,
            0,
            1,
            1,
            1,
            1,
            0,
            1,
            0,
            0,
            1,
            0,
            2,
            1,
            0,
            0,
            1,
            0,
            0,
            0,
            0,
            0,
            0,
            1,
            0,
            0,
            0,
            1,
            0,
            1,
            0,
            0,
            0,
            0,
            1,
            1,
            0,
            0,
            1,
            0,
            0,
            1,
            0,
            0,
            1,
            1,
            0,
            2,
            0,
            0,
            0,
            1,
            1,
            0,
            0,
            1,
            0,
            0,
            1,
            1,
            0,
            0,
            0,
            0,
            1,
            1,
            1,
            0,
            1,
            0,
            0,
            0,
            0,
            1,
            0,
            0,
            1,
            0,
            0,
            1,
            1,
            0,
            1,
            0,
            1,
            1,
            1,
            0,
            1,
            1,
            0,
            0,
            0,
            1,
            0,
            1,
            1,
            1,
            0,
            0,
            1,
            1,
            0,
            0,
            0,
            0,
            0,
            0,
            0,
            0,
            0,
            2,
            1,
            1,
            1,
            0,
            1,
            0,
            0,
            0,
            0,
            0,
            1,
            0,
            0,
            1,
            0,
            0,
            0,
            0,
            0,
            0,
            0,
            0,
            1,
            0,
            0,
            0,
            0,
            0,
            1,
            0,
            0,
            0,
            0,
            0,
            1,
            1,
            0,
            1
        ],
        [
            0,
            0,
            0,
            2,
            0,
            1,
            0,
            1,
            1,
            0,
            0,
            1,
            0,
            0,
            0,
            0,
            1,
            0,
            0,
            0,
            0,
            1,
            0,
            0,
            1,
            0,
            1,
            0,
            0,
            0,
            1,
            0,
            0,
            0,
            0,
            0,
            0,
            1,
            0,
            1,
            1,
            1,
            0,
            0,
            0,
            0,
            0,
            1,
            0,
            0,
            0,
            0,
            0,
            0,
            1,
            1,
            0,
            1,
            0,
            0,
            0,
            0,
            0,
            0,
            0,
            0,
            0,
            0,
            0,
            0,
            1,
            1,
            0,
            1,
            1,
            1,
            0,
            1,
            1,
            0,
            0,
            0,
            1,
            0,
            1,
            0,
            2,
            0,
            0,
            1,
            0,
            0,
            1,
            2,
            0,
            0,
            0,
            0,
            0,
            0,
            0,
            1,
            1,
            1,
            1,
            0,
            0,
            1,
            1,
            0,
            0,
            1,
            1,
            0,
            0,
            1,
            0,
            0,
            0,
            1,
            0,
            0,
            0,
            0,
            0,
            0,
            1,
            0,
            0,
            1,
            0,
            1,
            1,
            1,
            0,
            0,
            0,
            0,
            1,
            0,
            0,
            0,
            0,
            1,
            1,
            0,
            0,
            1,
            1,
            0,
            1,
            1,
            1,
            0,
            0,
            0,
            0,
            0,
            0,
            1,
            0,
            0,
            0,
            0,
            1,
            0,
            0,
            0,
            1,
            0,
            0,
            0,
            0,
            1,
            0,
            1,
            1,
            0,
            0,
            0,
            1,
            0,
            0,
            1,
            0,
            0,
            0,
            1,
            0,
            1,
            0,
            2,
            1,
            0,
            0,
            0,
            1,
            0,
            0,
            0,
            1,
            0,
            0,
            0,
            0,
            0,
            0,
            1,
            1,
            0,
            0,
            1,
            0,
            0,
            0,
            1,
            1,
            0,
            0,
            1,
            1,
            0,
            0,
            0,
            0,
            0,
            0,
            1,
            0,
            1,
            0,
            1,
            0,
            1,
            0,
            1,
            1,
            0,
            1,
            2,
            1,
            1,
            0,
            0,
            0,
            1,
            0,
            1,
            1,
            1,
            0,
            0,
            0,
            1,
            0,
            0,
            1,
            0,
            1,
            0
        ]
    ],
    "timestamp": 1570109522.1613045,
    "train_acc_list": [
        0.9346900141977788,
        0.9219119734973534,
        0.9423167848699318,
        0.9432624113474731,
        0.9177304964538573,
        0.9380614657209958,
        0.9304964539006652,
        0.9276595744680413,
        0.9437352245862438,
        0.9333333333332892
    ],
    "train_dp_acc": 0.002694100438378928,
    "train_mean_acc": 0.9333197732375629
}